[[{"left":486,"top":352,"right":612,"bottom":457,"class":"car","score":0.9362878799438477,"track_id":4}],null,null,null,null,null,null,null,null,null,null,null,null,null,null,null,null,null,null,null,null,null,null,null,null,null,null,null,null,null,null,null,[{"left":587,"top":222,"right":616,"bottom":245,"class":"car","score":0.7302626371383667,"track_id":15},{"left":542,"top":322,"right":641,"bottom":407,"class":"car","score":0.8992329239845276,"track_id":4}],null,null,null,null,null,null,null,null,null,null,null,null,null,null,null,null,null,null,null,null,null,null,null,null,null,null,null,null,null,null,null,[{"left":562,"top":220,"right":605,"bottom":252,"class":"car","score":0.779381275177002,"track_id":15},{"left":585,"top":297,"right":659,"bottom":360,"class":"car","score":0.6554820537567139,"track_id":4}],null,null,null,null,null,null,null,null,null,null,null,null,null,null,null,null,null,null,null,null,null,null,null,null,null,null,null,null,null,null,null,[{"left":540,"top":230,"right":582,"bottom":262,"class":"car","score":0.8659369349479675,"track_id":15},{"left":614,"top":275,"right":668,"bottom":327,"class":"car","score":0.9754617214202881,"track_id":4}],null,null,null,null,null,null,null,null,null,null,null,null,null,null,null,null,null,null,null,null,null,null,null,null,null,null,null,null,null,null,null,[{"left":524,"top":227,"right":564,"bottom":272,"class":"car","score":0.6096504330635071,"track_id":15},{"left":630,"top":260,"right":675,"bottom":300,"class":"car","score":0.977187991142273,"track_id":4}],null,null,null,null,null,null,null,null,null,null,null,null,null,null,null,null,null,null,null,null,null,null,null,null,null,null,null,null,null,null,null,[{"left":510,"top":235,"right":553,"bottom":277,"class":"car","score":0.8632916212081909,"track_id":15},{"left":641,"top":245,"right":679,"bottom":280,"class":"car","score":0.5683262348175049,"track_id":4}],null,null,null,null,null,null,null,null,null,null,null,null,null,null,null,null,null,null,null,null,null,null,null,null,null,null,null,null,null,null,null,[{"left":492,"top":237,"right":542,"bottom":285,"class":"car","score":0.951383650302887,"track_id":15},{"left":650,"top":237,"right":684,"bottom":262,"class":"car","score":0.4920159876346588,"track_id":4}],null,null,null,null,null,null,null,null,null,null,null,null,null,null,null,null,null,null,null,null,null,null,null,null,null,null,null,null,null,null,null,[{"left":465,"top":242,"right":522,"bottom":292,"class":"car","score":0.9711180925369263,"track_id":15},{"left":654,"top":222,"right":688,"bottom":250,"class":"car","score":0.6315732598304749,"track_id":4}],null,null,null,null,null,null,null,null,null,null,null,null,null,null,null,null,null,null,null,null,null,null,null,null,null,null,null,null,null,null,null,[{"left":411,"top":252,"right":483,"bottom":312,"class":"car","score":0.9781209826469421,"track_id":15}],null,null,null,null,null,null,null,null,null,null,null,null,null,null,null,null,null,null,null,null,null,null,null,null,null,null,null,null,null,null,null,[{"left":315,"top":277,"right":416,"bottom":347,"class":"car","score":0.9877721667289734,"track_id":15}],null,null,null,null,null,null,null,null,null,null,null,null,null,null,null,null,null,null,null,null,null,null,null,null,null,null,null,null,null,null,null,[{"left":132,"top":317,"right":274,"bottom":412,"class":"car","score":0.9850336909294128,"track_id":15}]]