[[{"left":392,"top":265,"right":437,"bottom":320,"class":"car","score":0.8855544924736023,"track_id":50}],null,null,null,null,null,null,null,[{"left":395,"top":249,"right":437,"bottom":300,"class":"car","score":0.880273699760437,"track_id":50}],null,null,null,null,null,null,null,[{"left":398,"top":234,"right":437,"bottom":280,"class":"car","score":0.8651505708694458,"track_id":50}],null,null,null,null,null,null,null,[{"left":401,"top":222,"right":438,"bottom":263,"class":"car","score":0.8819373846054077,"track_id":50}],null,null,null,null,null,null,null,[{"left":405,"top":209,"right":440,"bottom":248,"class":"car","score":0.8579617738723755,"track_id":50}],null,null,null,null,null,null,null,[{"left":406,"top":201,"right":440,"bottom":236,"class":"car","score":0.8706592917442322,"track_id":50}],null,null,null,null,null,null,null,[{"left":408,"top":191,"right":442,"bottom":224,"class":"car","score":0.8718950748443604,"track_id":50}],null,null,null,null,null,null,null,[{"left":409,"top":185,"right":444,"bottom":216,"class":"car","score":0.8615745306015015,"track_id":50}],null,null,null,null,null,null,null,[{"left":411,"top":177,"right":446,"bottom":208,"class":"car","score":0.8412225842475891,"track_id":50}],null,null,null,null,null,null,null,[{"left":413,"top":175,"right":447,"bottom":203,"class":"car","score":0.8433041572570801,"track_id":50}],null,null,null,null,null,null,null,[{"left":415,"top":171,"right":448,"bottom":197,"class":"car","score":0.8048825860023499,"track_id":50}],null,null,null,null,null,null,null,[{"left":417,"top":167,"right":449,"bottom":192,"class":"car","score":0.8456583619117737,"track_id":50}],null,null,null,null,null,null,null,[{"left":419,"top":164,"right":449,"bottom":189,"class":"car","score":0.8197354078292847,"track_id":50}],null,null,null,null,null,null,null,[{"left":420,"top":162,"right":450,"bottom":185,"class":"car","score":0.8056020736694336,"track_id":50}],null,null,null,null,null,null,null,[{"left":423,"top":160,"right":450,"bottom":183,"class":"car","score":0.822725772857666,"track_id":50}],null,null,null,null,null,null,null,[{"left":424,"top":158,"right":450,"bottom":182,"class":"car","score":0.8122689127922058,"track_id":50}],null,null,null,null,null,null,null,[{"left":423,"top":156,"right":450,"bottom":178,"class":"car","score":0.8021062016487122,"track_id":50}],null,null,null,null,null,null,null,[{"left":426,"top":153,"right":451,"bottom":177,"class":"car","score":0.7096765637397766,"track_id":50}],null,null,null,null,null,null,null,[{"left":423,"top":153,"right":450,"bottom":176,"class":"car","score":0.6260861158370972,"track_id":50}],null,null,null,null,null,null,null,[{"left":428,"top":153,"right":451,"bottom":175,"class":"car","score":0.8302931785583496,"track_id":50}],null,null,null,null,null,null,null,[{"left":427,"top":152,"right":451,"bottom":174,"class":"car","score":0.8410534858703613,"track_id":50}],null,null,null,null,null,null,null,[{"left":427,"top":152,"right":451,"bottom":174,"class":"car","score":0.8264729976654053,"track_id":50}],null,null,null,null,null,null,null,null,null,null,null,null,null,null,null,[{"left":427,"top":151,"right":450,"bottom":174,"class":"car","score":0.8070015907287598,"track_id":50}],null,null,null,null,null,null,null,[{"left":428,"top":151,"right":452,"bottom":174,"class":"car","score":0.834420919418335,"track_id":50}],null,null,null,null,null,null,null,[{"left":427,"top":151,"right":452,"bottom":174,"class":"car","score":0.8122117519378662,"track_id":50}],null,null,null,null,null,null,null,[{"left":427,"top":151,"right":451,"bottom":174,"class":"car","score":0.841430127620697,"track_id":50}],null,null,null,null,null,null,null,null,null,null,null,null,null,null,null,[{"left":428,"top":151,"right":450,"bottom":174,"class":"car","score":0.8076218962669373,"track_id":50}],null,null,null,null,null,null,null,[{"left":428,"top":151,"right":451,"bottom":174,"class":"car","score":0.8121082782745361,"track_id":50}],null,null,null,null,null,null,null,[{"left":427,"top":152,"right":450,"bottom":174,"class":"car","score":0.8364301919937134,"track_id":50}],null,null,null,null,null,null,null,[{"left":427,"top":152,"right":451,"bottom":175,"class":"car","score":0.8097885847091675,"track_id":50}],null,null,null,null,null,null,null,[{"left":426,"top":152,"right":451,"bottom":175,"class":"car","score":0.8017838001251221,"track_id":50}],null,null,null,null,null,null,null,[{"left":428,"top":152,"right":451,"bottom":175,"class":"car","score":0.8151262402534485,"track_id":50}],null,null,null,null,null,null,null,null,null,null,null,null,null,null,null,[{"left":428,"top":152,"right":450,"bottom":175,"class":"car","score":0.8432218432426453,"track_id":50}],null,null,null,null,null,null,null,[{"left":427,"top":152,"right":450,"bottom":175,"class":"car","score":0.8433306813240051,"track_id":50}],null,null,null,null,null,null,null,[{"left":427,"top":152,"right":450,"bottom":175,"class":"car","score":0.8419527411460876,"track_id":50}],null,null,null,null,null,null,null,[{"left":427,"top":153,"right":450,"bottom":175,"class":"car","score":0.8267306089401245,"track_id":50}],null,null,null,null,null,null,null,[{"left":426,"top":153,"right":450,"bottom":175,"class":"car","score":0.8166177272796631,"track_id":50}],null,null,null,null,null,null,null,[{"left":426,"top":153,"right":451,"bottom":175,"class":"car","score":0.8219128847122192,"track_id":50}],null,null,null,null,null,null,null,[{"left":427,"top":153,"right":451,"bottom":175,"class":"car","score":0.8302673101425171,"track_id":50}],null,null,null,null,null,null,null,[{"left":427,"top":153,"right":450,"bottom":175,"class":"car","score":0.8299297094345093,"track_id":50}],null,null,null,null,null,null,null,null,null,null,null,null,null,null,null,[{"left":426,"top":153,"right":450,"bottom":175,"class":"car","score":0.8022526502609253,"track_id":50}],null,null,null,null,null,null,null,[{"left":427,"top":153,"right":450,"bottom":175,"class":"car","score":0.7752805352210999,"track_id":50}],null,null,null,null,null,null,null,[{"left":427,"top":152,"right":450,"bottom":175,"class":"car","score":0.7628176808357239,"track_id":50}],null,null,null,null,null,null,null,null,null,null,null,null,null,null,null,null,null,null,null,null,null,null,null,null,null,null,null,null,null,null,null,[{"left":427,"top":151,"right":450,"bottom":175,"class":"car","score":0.7570926547050476,"track_id":50}],null,null,null,null,null,null,null,null,null,null,null,null,null,null,null,[{"left":426,"top":153,"right":451,"bottom":175,"class":"car","score":0.7938070893287659,"track_id":50}],null,null,null,null,null,null,null,[{"left":457,"top":162,"right":483,"bottom":189,"class":"car","score":0.24144624173641205,"track_id":50}],null,null,null,null,null,null,null,[{"left":458,"top":163,"right":484,"bottom":191,"class":"car","score":0.134668231010437,"track_id":50}],null,null,null,null,null,null,null,[{"left":427,"top":154,"right":451,"bottom":175,"class":"car","score":0.7549623847007751,"track_id":50}],null,null,null,null,null,null,null,[{"left":457,"top":161,"right":483,"bottom":190,"class":"car","score":0.13923734426498413,"track_id":50}],null,null,null,null,null,null,null,[{"left":456,"top":162,"right":483,"bottom":188,"class":"car","score":0.1261899620294571,"track_id":50}],null,null,null,null,null,null,null,[{"left":456,"top":161,"right":483,"bottom":188,"class":"car","score":0.16161711513996124,"track_id":50}],null,null,null,null,null,null,null,[{"left":428,"top":151,"right":451,"bottom":174,"class":"car","score":0.7076265215873718,"track_id":50}],null,null,null,null,null,null,null,[{"left":457,"top":159,"right":483,"bottom":188,"class":"car","score":0.1929776966571808,"track_id":50}],null,null,null,null,null,null,null,[{"left":456,"top":160,"right":482,"bottom":188,"class":"car","score":0.14326408505439758,"track_id":50}],null,null,null,null,null,null,null,[{"left":429,"top":151,"right":455,"bottom":173,"class":"car","score":0.84540855884552,"track_id":50}],null,null,null,null,null,null,null,[{"left":430,"top":151,"right":455,"bottom":171,"class":"car","score":0.7374937534332275,"track_id":50}],null,null,null,null,null,null,null,[{"left":458,"top":160,"right":483,"bottom":188,"class":"car","score":0.32016482949256897,"track_id":50}],null,null,null,null,null,null,null,[{"left":459,"top":163,"right":483,"bottom":188,"class":"car","score":0.20442025363445282,"track_id":50}],null,null,null,null,null,null,null,[{"left":459,"top":162,"right":484,"bottom":186,"class":"car","score":0.20523422956466675,"track_id":50}],null,null,null,null,null,null,null,[{"left":459,"top":163,"right":487,"bottom":197,"class":"car","score":0.3290071189403534,"track_id":50}],null,null,null,null,null,null,null,[{"left":460,"top":140,"right":484,"bottom":163,"class":"car","score":0.1825927495956421,"track_id":50}],null,null,null,null,null,null,null,null,null,null,null,null,null,null,null,null,null,null,null,null,null,null,null,null,null,null,null,null,null,null,null,[{"left":450,"top":144,"right":482,"bottom":160,"class":"car","score":0.7688720226287842,"track_id":50}],null,null,null,null,null,null,null,[{"left":456,"top":143,"right":491,"bottom":161,"class":"car","score":0.5869618058204651,"track_id":50}]]